dFF/dFF.vhd
LIBRARY ieee;
USE ieee.std_logic_1164.ALL;
USE IEEE.NUMERIC_STD.ALL;

ENTITY dFF IS
    PORT (
        clk : IN std_logic;
        D : IN std_logic;
        Q : OUT std_logic := '0'
    );
END ENTITY;

ARCHITECTURE main OF dFF IS
    SIGNAL delay: std_logic := '0';
    SIGNAL delay1: std_logic := '0';
BEGIN
    process(clk)
    begin
        IF rising_edge(clk) THEN
            Q <= D;
        END IF;
    end process;
END ARCHITECTURE;

adderGeneric/adderGeneric.vhd
LIBRARY ieee;
USE ieee.std_logic_1164.ALL;
USE IEEE.NUMERIC_STD.ALL;

ENTITY adderGeneric IS
    GENERIC( size: integer);
    PORT (
        in1 : IN std_logic_vector (size-2 DOWNTO 0):= (others => '0');
        in2 : IN std_logic_vector (size-2 DOWNTO 0):= (others => '0');
        q : OUT std_logic_vector (size-1 DOWNTO 0)
    );
END ENTITY;

ARCHITECTURE main OF adderGeneric IS
    SIGNAL sum : unsigned (size-1 DOWNTO 0):= (others => '0');
BEGIN
    sum <= unsigned('0'&in1) + unsigned(in2);
    q <= std_logic_vector(sum);
END ARCHITECTURE;

registerGeneric/registerGeneric.vhd
LIBRARY ieee;
USE ieee.std_logic_1164.ALL;
USE IEEE.NUMERIC_STD.ALL;

ENTITY registerGeneric IS
    GENERIC( size: integer);
    PORT (
        clk : IN std_logic;
        load : IN std_logic;
        d :IN std_logic_vector (size-1 DOWNTO 0);
        q : OUT std_logic_vector (size-1 DOWNTO 0):= (others => '0')
    );
END ENTITY;

ARCHITECTURE main OF registerGeneric IS
BEGIN
    PROCESS (clk,load) BEGIN
        IF (rising_edge(clk)) THEN
            IF(load = '1') THEN
                q <= d;
            END IF;
        END IF;
    END PROCESS;
END ARCHITECTURE;

counterGeneric/counterGeneric.vhd
LIBRARY ieee;
USE ieee.std_logic_1164.ALL;
USE IEEE.NUMERIC_STD.ALL;

ENTITY counterGeneric IS
    GENERIC( size: integer);
    PORT (
        clk : IN std_logic;
        reset : IN std_logic;
        q : OUT std_logic_vector (size-1 DOWNTO 0):= (others => '0')
    );
END ENTITY;

ARCHITECTURE main OF counterGeneric IS
    SIGNAL count : unsigned (size-1 DOWNTO 0):= (others => '0');
BEGIN
    PROCESS (clk, reset) BEGIN
        IF (reset = '1') THEN
            count <= (OTHERS => '0');
        ELSIF (rising_edge(clk)) THEN
            count <= count + 1;
        END IF;
    END PROCESS;
    q <= std_logic_vector(count);
END ARCHITECTURE;

processor/processor.vhd
LIBRARY ieee;
USE ieee.std_logic_1164.ALL;
USE IEEE.NUMERIC_STD.ALL;

ENTITY processor IS
    PORT (
        clk : IN std_logic;
        Hall : IN std_logic;
        LED : OUT std_logic_vector(5 DOWNTO 0);
        test : OUT std_logic
    );
END ENTITY;

ARCHITECTURE main OF processor IS
    CONSTANT PCWidth : integer := 6;
    SIGNAL dFFOut : std_logic := '0';
    SIGNAL dFFWrite : std_logic;
    SIGNAL tEndWrite : std_logic;
    SIGNAL tStartWrite : std_logic;
    SIGNAL PC : std_logic_vector(PCWidth-1 DOWNTO 0);
    SIGNAL T1 : std_logic_vector(PCWidth DOWNTO 0);
    SIGNAL T1_Adder: std_logic_vector(PCWidth DOWNTO 0):= (others => '0');
    SIGNAL T2: std_logic_vector(PCWidth DOWNTO 0);
    SIGNAL T2_processed: std_logic_vector(PCWidth DOWNTO 0);
    SIGNAL tEndClock : std_logic_vector(PCWidth-1 DOWNTO 0);
    SIGNAL tStartClock : std_logic_vector(PCWidth-1 DOWNTO 0);
    SIGNAL T1Write : std_logic;
    COMPONENT counterGeneric is
        generic(size: integer);
        port(clk, reset: IN std_logic;
        q: OUT std_logic_vector(PCWidth-1 DOWNTO 0));
    END COMPONENT;
    COMPONENT adderGeneric is
        generic(size: integer);
        port(in1, in2: IN std_logic_vector(PCWidth-1 DOWNTO 0);
        q: OUT std_logic_vector(PCWidth DOWNTO 0));
    END COMPONENT;
    COMPONENT registerGeneric is
        generic(size: integer);
        port(clk,load: IN std_logic;
        d: IN std_logic_vector(size-1 DOWNTO 0);
        q: OUT std_logic_vector(size-1 DOWNTO 0));
    END COMPONENT;
    COMPONENT dFF is
        port(clk, D: IN std_logic;
        Q: OUT std_logic);
    END COMPONENT;
BEGIN
    programCounter: counterGeneric GENERIC MAP(PCWidth) PORT MAP(clk, '0', PC);
    tStartRegister: registerGeneric GENERIC MAP(PCWidth) PORT MAP(clk,tStartWrite, PC,tStartClock);
    tEndRegister: registerGeneric GENERIC MAP(PCWidth) PORT MAP(tEndWrite,tEndWrite, PC,tEndClock);
    T2Register: registerGeneric GENERIC MAP(PCWidth+1) PORT MAP(tEndWrite,tEndWrite, T1,T2);
    T1Register: registerGeneric GENERIC MAP(PCWidth+1) PORT MAP(clk,T1Write, T1_Adder,T1);
    T1Adder: adderGeneric GENERIC MAP(PCWidth+1) PORT MAP(tStartClock,tEndClock,T1_Adder);
    hallDFF: dFF PORT MAP(clk, Hall, dFFOut);
    tStartWrite <= (Hall AND (NOT (dFFOut))) AND clk;
    tEndWrite <= (NOT (Hall) AND dFFOut) AND clk;
    LED <= PC;
    PROCESS (clk) 
    BEGIN   
        IF rising_edge(clk) THEN
            T1Write <= tEndWrite;
        END IF;
    END PROCESS;
END ARCHITECTURE;

processor/processor_tb.vhd
LIBRARY IEEE;
USE IEEE.STD_LOGIC_1164.ALL;
USE IEEE.NUMERIC_STD.ALL;
USE work.bookUtility.ALL; -- for toString
USE std.textio.ALL;

ENTITY processor_tb IS
END;

ARCHITECTURE bench OF processor_tb IS
  SIGNAL tHall : STD_LOGIC;
  SIGNAL tLED : STD_LOGIC;
  SIGNAL tTest : STD_LOGIC_VECTOR(5 DOWNTO 0);
  SIGNAL tTestUn : STD_LOGIC;
  SIGNAL tClk : STD_LOGIC := '0';
  SIGNAL clockEnable : STD_LOGIC := '1';

BEGIN

  clock : PROCESS

  BEGIN
    WHILE clockEnable = '1' LOOP
      WAIT FOR 5 ns;
      tClk <= NOT tClk;
      -- REPORT "Clock tick [" & std_logic'image(tClk) & "]";
    END LOOP;
    WAIT;
  END PROCESS;

  testing : PROCESS

    FILE log : text OPEN write_mode IS "counter4b.txt";
    VARIABLE row : line;

    PROCEDURE vypis IS
    BEGIN
      --write(row, tQ, left, 5);
      --write(row, tD, left, 5);
      --writeline(log, row);
    END PROCEDURE;

  BEGIN
    tHall <= '0';
    --ASSERT tQ = "0" REPORT "reset failed" SEVERITY failure;

    WAIT FOR 10 ns; --count up
    vypis;

    --ASSERT tQ = "0" REPORT "count 0001" SEVERITY failure;
    WAIT FOR 10 ns; --count up
    vypis;

    tHall <= '1';
    WAIT FOR 60 ns; --count up
    tHall <= '0';
    WAIT FOR 50 ns; --count up
    tHall <= '1';
    WAIT FOR 60 ns; --count up
    tHall <= '0';
    WAIT FOR 50 ns; --count up
    tHall <= '1';
    WAIT FOR 60 ns; --count up
    tHall <= '0';
    WAIT FOR 40 ns; --count up
    -- end
    clockEnable <= '0';
    REPORT "Test OK";
    WAIT;

  END PROCESS;

  UUT : ENTITY work.processor PORT MAP(tClk, tHall,tTest,tTestUn);

END bench;

tests/processor.vcd
$date
  Sat Aug 19 22:34:20 2023
$end
$version
  GHDL v0
$end
$timescale
  1 fs
$end
$scope module standard $end
$upscope $end
$scope module std_logic_1164 $end
$upscope $end
$scope module numeric_std $end
$upscope $end
$scope module bookutility $end
$upscope $end
$scope module textio $end
$upscope $end
$scope module processor_tb $end
$var reg 1 ! thall $end
$var reg 1 " tled $end
$var reg 6 # ttest[5:0] $end
$var reg 1 $ ttestun $end
$var reg 1 % tclk $end
$var reg 1 & clockenable $end
$scope module uut $end
$var reg 1 ' clk $end
$var reg 1 ( hall $end
$var reg 6 ) led[5:0] $end
$var reg 1 * test $end
$var reg 1 + dffout $end
$var reg 1 , dffwrite $end
$var reg 1 - tendwrite $end
$var reg 1 . tstartwrite $end
$var reg 6 / pc[5:0] $end
$var reg 7 0 t1[6:0] $end
$var reg 7 1 t1_adder[6:0] $end
$var reg 7 2 t2[6:0] $end
$var reg 7 3 t2_processed[6:0] $end
$var reg 6 4 tendclock[5:0] $end
$var reg 6 5 tstartclock[5:0] $end
$var reg 1 6 t1write $end
$scope module programcounter $end
$var reg 1 7 clk $end
$var reg 1 8 reset $end
$var reg 6 9 q[5:0] $end
$var reg 6 : count[5:0] $end
$upscope $end
$scope module tstartregister $end
$var reg 1 ; clk $end
$var reg 1 < load $end
$var reg 6 = d[5:0] $end
$var reg 6 > q[5:0] $end
$upscope $end
$scope module tendregister $end
$var reg 1 ? clk $end
$var reg 1 @ load $end
$var reg 6 A d[5:0] $end
$var reg 6 B q[5:0] $end
$upscope $end
$scope module t2register $end
$var reg 1 C clk $end
$var reg 1 D load $end
$var reg 7 E d[6:0] $end
$var reg 7 F q[6:0] $end
$upscope $end
$scope module t1register $end
$var reg 1 G clk $end
$var reg 1 H load $end
$var reg 7 I d[6:0] $end
$var reg 7 J q[6:0] $end
$upscope $end
$scope module t1adder $end
$var reg 6 K in1[5:0] $end
$var reg 6 L in2[5:0] $end
$var reg 7 M q[6:0] $end
$var reg 7 N sum[6:0] $end
$upscope $end
$scope module halldff $end
$var reg 1 O clk $end
$var reg 1 P d $end
$var reg 1 Q q $end
$var reg 1 R delay $end
$var reg 1 S delay1 $end
$upscope $end
$upscope $end
$upscope $end
$enddefinitions $end
#0
0!
U"
b000000 #
U$
0%
1&
0'
0(
b000000 )
U*
0+
U,
0-
0.
b000000 /
b0000000 0
b0000000 1
b0000000 2
bUUUUUUU 3
b000000 4
b000000 5
U6
07
08
b000000 9
b000000 :
0;
0<
b000000 =
b000000 >
0?
0@
b000000 A
b000000 B
0C
0D
b0000000 E
b0000000 F
0G
UH
b0000000 I
b0000000 J
b000000 K
b000000 L
b0000000 M
b0000000 N
0O
0P
0Q
0R
0S
#5000000
b000001 #
1%
1'
b000001 )
b000001 /
06
17
b000001 9
b000001 :
1;
b000001 =
b000001 A
1G
0H
1O
#10000000
0%
0'
07
0;
0G
0O
#15000000
b000010 #
1%
1'
b000010 )
b000010 /
17
b000010 9
b000010 :
1;
b000010 =
b000010 A
1G
1O
#20000000
1!
0%
0'
1(
07
0;
0G
0O
1P
#25000000
b000011 #
1%
1'
b000011 )
1+
0.
b000011 /
17
b000011 9
b000011 :
1;
0<
b000011 =
b000011 A
1G
1O
1Q
#30000000
0%
0'
07
0;
0G
0O
#35000000
b000100 #
1%
1'
b000100 )
b000100 /
17
b000100 9
b000100 :
1;
b000100 =
b000100 A
1G
1O
#40000000
0%
0'
07
0;
0G
0O
#45000000
b000101 #
1%
1'
b000101 )
b000101 /
17
b000101 9
b000101 :
1;
b000101 =
b000101 A
1G
1O
#50000000
0%
0'
07
0;
0G
0O
#55000000
b000110 #
1%
1'
b000110 )
b000110 /
17
b000110 9
b000110 :
1;
b000110 =
b000110 A
1G
1O
#60000000
0%
0'
07
0;
0G
0O
#65000000
b000111 #
1%
1'
b000111 )
b000111 /
17
b000111 9
b000111 :
1;
b000111 =
b000111 A
1G
1O
#70000000
0%
0'
07
0;
0G
0O
#75000000
b001000 #
1%
1'
b001000 )
b001000 /
17
b001000 9
b001000 :
1;
b001000 =
b001000 A
1G
1O
#80000000
0!
0%
0'
0(
07
0;
0G
0O
0P
#85000000
b001001 #
1%
1'
b001001 )
0+
0-
b001001 /
b0001000 1
b001000 4
17
b001001 9
b001001 :
1;
b001001 =
0?
0@
b001001 A
b001000 B
0C
0D
1G
b0001000 I
b001000 L
b0001000 M
b0001000 N
1O
0Q
#90000000
0%
0'
07
0;
0G
0O
#95000000
b001010 #
1%
1'
b001010 )
b001010 /
17
b001010 9
b001010 :
1;
b001010 =
b001010 A
1G
1O
#100000000
0%
0'
07
0;
0G
0O
#105000000
b001011 #
1%
1'
b001011 )
b001011 /
17
b001011 9
b001011 :
1;
b001011 =
b001011 A
1G
1O
#110000000
0%
0'
07
0;
0G
0O
#115000000
b001100 #
1%
1'
b001100 )
b001100 /
17
b001100 9
b001100 :
1;
b001100 =
b001100 A
1G
1O
#120000000
0%
0'
07
0;
0G
0O
#125000000
b001101 #
1%
1'
b001101 )
b001101 /
17
b001101 9
b001101 :
1;
b001101 =
b001101 A
1G
1O
#130000000
1!
0%
0'
1(
07
0;
0G
0O
1P
#135000000
b001110 #
1%
1'
b001110 )
1+
0.
b001110 /
17
b001110 9
b001110 :
1;
0<
b001110 =
b001110 A
1G
1O
1Q
#140000000
0%
0'
07
0;
0G
0O
#145000000
b001111 #
1%
1'
b001111 )
b001111 /
17
b001111 9
b001111 :
1;
b001111 =
b001111 A
1G
1O
#150000000
0%
0'
07
0;
0G
0O
#155000000
b010000 #
1%
1'
b010000 )
b010000 /
17
b010000 9
b010000 :
1;
b010000 =
b010000 A
1G
1O
#160000000
0%
0'
07
0;
0G
0O
#165000000
b010001 #
1%
1'
b010001 )
b010001 /
17
b010001 9
b010001 :
1;
b010001 =
b010001 A
1G
1O
#170000000
0%
0'
07
0;
0G
0O
#175000000
b010010 #
1%
1'
b010010 )
b010010 /
17
b010010 9
b010010 :
1;
b010010 =
b010010 A
1G
1O
#180000000
0%
0'
07
0;
0G
0O
#185000000
b010011 #
1%
1'
b010011 )
b010011 /
17
b010011 9
b010011 :
1;
b010011 =
b010011 A
1G
1O
#190000000
0!
0%
0'
0(
07
0;
0G
0O
0P
#195000000
b010100 #
1%
1'
b010100 )
0+
0-
b010100 /
b0010011 1
b010011 4
17
b010100 9
b010100 :
1;
b010100 =
0?
0@
b010100 A
b010011 B
0C
0D
1G
b0010011 I
b010011 L
b0010011 M
b0010011 N
1O
0Q
#200000000
0%
0'
07
0;
0G
0O
#205000000
b010101 #
1%
1'
b010101 )
b010101 /
17
b010101 9
b010101 :
1;
b010101 =
b010101 A
1G
1O
#210000000
0%
0'
07
0;
0G
0O
#215000000
b010110 #
1%
1'
b010110 )
b010110 /
17
b010110 9
b010110 :
1;
b010110 =
b010110 A
1G
1O
#220000000
0%
0'
07
0;
0G
0O
#225000000
b010111 #
1%
1'
b010111 )
b010111 /
17
b010111 9
b010111 :
1;
b010111 =
b010111 A
1G
1O
#230000000
0%
0'
07
0;
0G
0O
#235000000
b011000 #
1%
1'
b011000 )
b011000 /
17
b011000 9
b011000 :
1;
b011000 =
b011000 A
1G
1O
#240000000
1!
0%
0'
1(
07
0;
0G
0O
1P
#245000000
b011001 #
1%
1'
b011001 )
1+
0.
b011001 /
17
b011001 9
b011001 :
1;
0<
b011001 =
b011001 A
1G
1O
1Q
#250000000
0%
0'
07
0;
0G
0O
#255000000
b011010 #
1%
1'
b011010 )
b011010 /
17
b011010 9
b011010 :
1;
b011010 =
b011010 A
1G
1O
#260000000
0%
0'
07
0;
0G
0O
#265000000
b011011 #
1%
1'
b011011 )
b011011 /
17
b011011 9
b011011 :
1;
b011011 =
b011011 A
1G
1O
#270000000
0%
0'
07
0;
0G
0O
#275000000
b011100 #
1%
1'
b011100 )
b011100 /
17
b011100 9
b011100 :
1;
b011100 =
b011100 A
1G
1O
#280000000
0%
0'
07
0;
0G
0O
#285000000
b011101 #
1%
1'
b011101 )
b011101 /
17
b011101 9
b011101 :
1;
b011101 =
b011101 A
1G
1O
#290000000
0%
0'
07
0;
0G
0O
#295000000
b011110 #
1%
1'
b011110 )
b011110 /
17
b011110 9
b011110 :
1;
b011110 =
b011110 A
1G
1O
#300000000
0!
0%
0'
0(
07
0;
0G
0O
0P
#305000000
b011111 #
1%
1'
b011111 )
0+
0-
b011111 /
b0011110 1
b011110 4
17
b011111 9
b011111 :
1;
b011111 =
0?
0@
b011111 A
b011110 B
0C
0D
1G
b0011110 I
b011110 L
b0011110 M
b0011110 N
1O
0Q
#310000000
0%
0'
07
0;
0G
0O
#315000000
b100000 #
1%
1'
b100000 )
b100000 /
17
b100000 9
b100000 :
1;
b100000 =
b100000 A
1G
1O
#320000000
0%
0'
07
0;
0G
0O
#325000000
b100001 #
1%
1'
b100001 )
b100001 /
17
b100001 9
b100001 :
1;
b100001 =
b100001 A
1G
1O
#330000000
0%
0'
07
0;
0G
0O
#335000000
b100010 #
1%
1'
b100010 )
b100010 /
17
b100010 9
b100010 :
1;
b100010 =
b100010 A
1G
1O
#340000000
0%
0&
0'
07
0;
0G
0O
#345000000
b100011 #
1%
1'
b100011 )
b100011 /
17
b100011 9
b100011 :
1;
b100011 =
b100011 A
1G
1O
